simo_sdk/__init__.py
simo_sdk/client.py
simo_sdk/collections.py
simo_sdk/exceptions.py
simo_sdk/models.py
simo_sdk/mqtt.py
simo_sdk/rest.py
simo_sdk/store.py
simo_sdk/sun.py
simo_sdk/types.py
simo_sdk/unix_socket.py
simo_sdk/tests/__init__.py
simo_sdk/tests/test_env_defaults.py
simo_sdk/tests/test_on_change_since.py
simo_sdk-1.1.2.dist-info/METADATA
simo_sdk-1.1.2.dist-info/WHEEL
simo_sdk-1.1.2.dist-info/top_level.txt
simo_sdk-1.1.2.dist-info/RECORD
