Metadata-Version: 2.4
Name: simo-sdk
Version: 1.1.2
Summary: Python SDK for controlling SIMO.io smart homes over REST+MQTT
Author-email: "Simon V." <simon@simo.io>
Classifier: Programming Language :: Python :: 3
Classifier: Operating System :: OS Independent
Requires-Python: >=3.10
Requires-Dist: requests>=2.31
Requires-Dist: paho-mqtt>=1.6
Requires-Dist: suntime>=1.3
